fseasypygame/__init__.py
fseasypygame-0.2.1.dist-info/LICENSE
fseasypygame-0.2.1.dist-info/METADATA
fseasypygame-0.2.1.dist-info/WHEEL
fseasypygame-0.2.1.dist-info/top_level.txt
fseasypygame-0.2.1.dist-info/RECORD
