Metadata-Version: 2.1
Name: fseasypygame
Version: 0.2.1
Summary: A simplified pygame wrapper for easier game development
Home-page: https://github.com/madhat386/fseasypygame
Author: madhat
Author-email: madhat625@gmail.com
Classifier: Programming Language :: Python :: 3
Classifier: License :: OSI Approved :: MIT License
Classifier: Operating System :: OS Independent
Requires-Python: >=3.7
License-File: LICENSE
Requires-Dist: pygame >=2.5.1
